{
  "carInformation": [
    {
      "id": 1,
      "plateNUmber": "KSF230FG",
      "Insurance": "yes",
      "Licence": "yes",
      "Road Worthiness": "yes"
    },
    {
      "id": 2,
      "plateNUmber": "BVX456MN",
      "Insurance": "yes",
      "Licence": "yes",
      "Road Worthiness": "no"
    },
    {
      "id": 3,
      "plateNUmber": "SJF470TY",
      "Insurance": "no",
      "Licence": "yes",
      "Road Worthiness": "yes"
    },
    {
      "id": 4,
      "plateNUmber": "POL857CN",
      "Insurance": "yes",
      "Licence": "no",
      "Road Worthiness": "yes"
    },
    {
      "id": 5,
      "plateNUmber": "BOJ888DJ",
      "Insurance": "no",
      "Licence": "no",
      "Road Worthiness": "no"
    },
    {
      "id": 6,
      "plateNUmber": "DEFENCE002",
      "Insurance": "no",
      "Licence": "no",
      "Road Worthiness": "yes"
    }
  ]
}
